nldesa/__init__.py
nldesa/_objects.py
nldesa/_utils.py
nldesa-0.0.3.dist-info/METADATA
nldesa-0.0.3.dist-info/WHEEL
nldesa-0.0.3.dist-info/top_level.txt
nldesa-0.0.3.dist-info/RECORD
