Metadata-Version: 2.1
Name: nldesa
Version: 0.0.3
Summary: A package with tools to solve and analyse nonlinear differential equations Stability using DMD.
Home-page: https://github.com/joaopedrobiu6/nldesa/
Author: João Pedro Ferreira Biu, Miguel de Oliveira Lameiras
Author-email: João Pedro Ferreira Biu <joaopedrofbiu@tecnico.ulisboa.pt>, Miguel de Oliveira Lameiras <miguel.lameiras@tecnico.ulisboa.pt>
License: MIT
Project-URL: Homepage, https://github.com/joaopedrobiu6/nldesa/
Project-URL: Bug Tracker, https://github.com/joaopedrobiu6/nldesa/issues/
Keywords: differential equations,stability analysis,nonlinear systems,jax,odeint
Classifier: Programming Language :: Python :: 3
Classifier: License :: OSI Approved :: MIT License
Classifier: Operating System :: OS Independent
Requires-Python: >=3.8
Requires-Dist: pydmd
Requires-Dist: jax[cpu]
Requires-Dist: numpy <1.25.0,>=1.20.0
Requires-Dist: scipy <1.11.0,>=1.5.0
